pymongoexplain/__init__.py
pymongoexplain/__main__.py
pymongoexplain/commands.py
pymongoexplain/explainable_collection.py
pymongoexplain/utils.py
pymongoexplain/version.py
pymongoexplain-1.2.0.dist-info/LICENSE
pymongoexplain-1.2.0.dist-info/METADATA
pymongoexplain-1.2.0.dist-info/WHEEL
pymongoexplain-1.2.0.dist-info/entry_points.txt
pymongoexplain-1.2.0.dist-info/top_level.txt
pymongoexplain-1.2.0.dist-info/RECORD
